{
  "project_info": {
    "project_number": "945203598586",
    "project_id": "flutter-chat-app-aee01",
    "storage_bucket": "flutter-chat-app-aee01.appspot.com"
  },
  "client": [
    {
      "client_info": {
        "mobilesdk_app_id": "1:945203598586:android:e5b4266f8673091b956543",
        "android_client_info": {
          "package_name": "com.example.chat_app"
        }
      },
      "oauth_client": [],
      "api_key": [
        {
          "current_key": "AIzaSyCRGpID6IjPwdhk5HaVUeX12unVtY4rWas"
        }
      ],
      "services": {
        "appinvite_service": {
          "other_platform_oauth_client": []
        }
      }
    }
  ],
  "configuration_version": "1"
}